{"__type__":"dragonBones.DragonBonesAtlasAsset","_name":"lightningBall1","_atlasJson":"{\"name\":\"lightningBall1\",\"imagePath\":\"battleunits.png\",\"SubTexture\":[{\"name\":\"flyingObject/lightningBall1/0\",\"x\":1269,\"y\":154,\"width\":79,\"height\":43},{\"name\":\"flyingObject/lightningBall1/1\",\"x\":410,\"y\":257,\"width\":91,\"height\":43},{\"name\":\"flyingObject/lightningBall1/2\",\"x\":410,\"y\":302,\"width\":89,\"height\":43},{\"name\":\"flyingObject/lightningBall1/20001\",\"x\":229,\"y\":446,\"width\":20,\"height\":22},{\"name\":\"flyingObject/lightningBall1/20002\",\"x\":253,\"y\":1257,\"width\":46,\"height\":52},{\"name\":\"flyingObject/lightningBall1/20003\",\"x\":934,\"y\":544,\"width\":62,\"height\":66},{\"name\":\"flyingObject/lightningBall1/20004\",\"x\":1647,\"y\":418,\"width\":66,\"height\":68},{\"name\":\"flyingObject/lightningBall1/20005\",\"x\":1691,\"y\":2,\"width\":72,\"height\":56},{\"name\":\"flyingObject/lightningBall1/20006\",\"x\":731,\"y\":828,\"width\":56,\"height\":58},{\"name\":\"flyingObject/lightningBall1/3\",\"x\":252,\"y\":425,\"width\":83,\"height\":43}]}\n","texture":{"__uuid__":"aa2sKZWPxIhIOoamfWesSu"}}
