[[{"__type__":"cc.Prefab","_name":"jn_chuyin_gzhu","data":{"__id__":1},"asyncLoadAssets":null},{"__type__":"cc.Node","_name":"jn_chuyin_gzhu_ske","_components":[{"__type__":"dragonBones.ArmatureDisplay","node":{"__id__":1},"_armatureName":"jn_chuyin_gzhu","_N$dragonAsset":{"__uuid__":"bd58mzbwJNZqROWzG5hxIs"},"_N$dragonAtlasAsset":{"__uuid__":"d3x8l5StJPvLibVX1+Evpz"}}],"_prefab":{"__type__":"cc.PrefabInfo","root":{"__id__":1},"asset":{"__id__":0},"fileId":"ccGtpMTg1GNq4I/ypfUw59"}}],{"__type__":"dragonBones.DragonBonesAsset","_name":"jn_chuyin_gzhu_ske","_dragonBonesJson":"{\"frameRate\":18,\"isGlobal\":0,\"armature\":[{\"skin\":[{\"name\":\"\",\"slot\":[{\"display\":[{\"path\":\"jn_chuyin_gzhu07\",\"type\":\"image\",\"name\":\"jn_chuyin_gzhu07\",\"transform\":{}}],\"name\":\"jn_chuyin_gzhu07\"},{\"display\":[{\"path\":\"jn_chuyin_gzhu06\",\"type\":\"image\",\"name\":\"jn_chuyin_gzhu06\",\"transform\":{}}],\"name\":\"jn_chuyin_gzhu06\"},{\"display\":[{\"path\":\"jn_chuyin_gzhu01\",\"type\":\"image\",\"name\":\"jn_chuyin_gzhu01\",\"transform\":{}}],\"name\":\"jn_chuyin_gzhu01\"},{\"display\":[{\"path\":\"jn_chuyin_gzhu09\",\"type\":\"image\",\"name\":\"jn_chuyin_gzhu09\",\"transform\":{}}],\"name\":\"jn_chuyin_gzhu09\"},{\"display\":[{\"path\":\"jn_chuyin_gzhu03\",\"type\":\"image\",\"name\":\"jn_chuyin_gzhu03\",\"transform\":{}}],\"name\":\"jn_chuyin_gzhu03\"},{\"display\":[{\"path\":\"jn_chuyin_gzhu02\",\"type\":\"image\",\"name\":\"jn_chuyin_gzhu02\",\"transform\":{}}],\"name\":\"jn_chuyin_gzhu02\"},{\"display\":[{\"path\":\"jn_chuyin_gzhu010\",\"type\":\"image\",\"name\":\"jn_chuyin_gzhu010\",\"transform\":{}}],\"name\":\"jn_chuyin_gzhu010\"},{\"display\":[{\"path\":\"jn_chuyin_gzhu05\",\"type\":\"image\",\"name\":\"jn_chuyin_gzhu05\",\"transform\":{}}],\"name\":\"jn_chuyin_gzhu05\"},{\"display\":[{\"path\":\"jn_chuyin_gzhu04\",\"type\":\"image\",\"name\":\"jn_chuyin_gzhu04\",\"transform\":{}}],\"name\":\"jn_chuyin_gzhu04\"},{\"display\":[{\"path\":\"jn_chuyin_gzhu08\",\"type\":\"image\",\"name\":\"jn_chuyin_gzhu08\",\"transform\":{}}],\"name\":\"jn_chuyin_gzhu08\"}]}],\"bone\":[{\"name\":\"root\",\"transform\":{}},{\"transform\":{},\"name\":\"jn_chuyin_gzhu09\",\"parent\":\"root\"},{\"transform\":{},\"name\":\"jn_chuyin_gzhu08\",\"parent\":\"root\"},{\"transform\":{},\"name\":\"jn_chuyin_gzhu07\",\"parent\":\"root\"},{\"transform\":{},\"name\":\"jn_chuyin_gzhu06\",\"parent\":\"root\"},{\"transform\":{},\"name\":\"jn_chuyin_gzhu05\",\"parent\":\"root\"},{\"transform\":{},\"name\":\"jn_chuyin_gzhu04\",\"parent\":\"root\"},{\"transform\":{},\"name\":\"jn_chuyin_gzhu03\",\"parent\":\"root\"},{\"transform\":{},\"name\":\"jn_chuyin_gzhu02\",\"parent\":\"root\"},{\"transform\":{},\"name\":\"jn_chuyin_gzhu010\",\"parent\":\"root\"},{\"transform\":{},\"name\":\"jn_chuyin_gzhu01\",\"parent\":\"root\"}],\"defaultActions\":[{\"gotoAndPlay\":\"jn_chuyin_gzhu\"}],\"type\":\"MovieClip\",\"frameRate\":18,\"slot\":[{\"color\":{},\"name\":\"jn_chuyin_gzhu010\",\"parent\":\"jn_chuyin_gzhu010\",\"displayIndex\":-1},{\"z\":1,\"color\":{},\"name\":\"jn_chuyin_gzhu09\",\"parent\":\"jn_chuyin_gzhu09\",\"displayIndex\":-1},{\"z\":2,\"color\":{},\"name\":\"jn_chuyin_gzhu08\",\"parent\":\"jn_chuyin_gzhu08\",\"displayIndex\":-1},{\"z\":3,\"color\":{},\"name\":\"jn_chuyin_gzhu07\",\"parent\":\"jn_chuyin_gzhu07\",\"displayIndex\":-1},{\"z\":4,\"color\":{},\"name\":\"jn_chuyin_gzhu06\",\"parent\":\"jn_chuyin_gzhu06\",\"displayIndex\":-1},{\"z\":5,\"color\":{},\"name\":\"jn_chuyin_gzhu05\",\"parent\":\"jn_chuyin_gzhu05\",\"displayIndex\":-1},{\"z\":6,\"color\":{},\"name\":\"jn_chuyin_gzhu04\",\"parent\":\"jn_chuyin_gzhu04\",\"displayIndex\":-1},{\"z\":7,\"color\":{},\"name\":\"jn_chuyin_gzhu03\",\"parent\":\"jn_chuyin_gzhu03\",\"displayIndex\":-1},{\"z\":8,\"color\":{},\"name\":\"jn_chuyin_gzhu02\",\"parent\":\"jn_chuyin_gzhu02\",\"displayIndex\":-1},{\"z\":9,\"color\":{},\"name\":\"jn_chuyin_gzhu01\",\"parent\":\"jn_chuyin_gzhu01\",\"displayIndex\":-1}],\"animation\":[{\"bone\":[{\"frame\":[{\"transform\":{},\"duration\":11}],\"name\":\"root\"},{\"frame\":[{\"transform\":{},\"duration\":9},{\"transform\":{\"y\":-30},\"duration\":1},{\"transform\":{\"y\":-30},\"duration\":1}],\"name\":\"jn_chuyin_gzhu09\"},{\"frame\":[{\"transform\":{},\"duration\":8},{\"transform\":{\"y\":-30},\"duration\":1},{\"transform\":{\"y\":-30},\"duration\":2}],\"name\":\"jn_chuyin_gzhu08\"},{\"frame\":[{\"transform\":{},\"duration\":7},{\"transform\":{\"y\":-30},\"duration\":1},{\"transform\":{\"y\":-30},\"duration\":3}],\"name\":\"jn_chuyin_gzhu07\"},{\"frame\":[{\"transform\":{},\"duration\":6},{\"transform\":{\"y\":-30},\"duration\":1},{\"transform\":{\"y\":-30},\"duration\":4}],\"name\":\"jn_chuyin_gzhu06\"},{\"frame\":[{\"transform\":{},\"duration\":5},{\"transform\":{\"y\":-30},\"duration\":1},{\"transform\":{\"y\":-30},\"duration\":5}],\"name\":\"jn_chuyin_gzhu05\"},{\"frame\":[{\"transform\":{},\"duration\":4},{\"transform\":{\"y\":-30},\"duration\":1},{\"transform\":{\"y\":-30},\"duration\":6}],\"name\":\"jn_chuyin_gzhu04\"},{\"frame\":[{\"transform\":{},\"duration\":3},{\"transform\":{\"y\":-30},\"duration\":1},{\"transform\":{\"y\":-30},\"duration\":7}],\"name\":\"jn_chuyin_gzhu03\"},{\"frame\":[{\"transform\":{},\"duration\":2},{\"transform\":{\"y\":-30},\"duration\":1},{\"transform\":{\"y\":-30},\"duration\":8}],\"name\":\"jn_chuyin_gzhu02\"},{\"frame\":[{\"transform\":{},\"duration\":10},{\"transform\":{\"y\":-30},\"duration\":1},{\"transform\":{\"y\":-30},\"duration\":0}],\"name\":\"jn_chuyin_gzhu010\"},{\"frame\":[{\"transform\":{},\"duration\":1},{\"transform\":{\"y\":-30},\"duration\":1},{\"transform\":{\"y\":-30},\"duration\":9}],\"name\":\"jn_chuyin_gzhu01\"}],\"frame\":[{\"duration\":10,\"tweenEasing\":null},{\"tweenEasing\":null,\"event\":\"fire\",\"duration\":0}],\"slot\":[{\"frame\":[{\"tweenEasing\":null,\"duration\":9,\"displayIndex\":-1},{\"tweenEasing\":null,\"duration\":1},{\"tweenEasing\":null,\"duration\":1,\"color\":{\"aM\":0}}],\"name\":\"jn_chuyin_gzhu09\"},{\"frame\":[{\"tweenEasing\":null,\"duration\":8,\"displayIndex\":-1},{\"tweenEasing\":null,\"duration\":1},{\"tweenEasing\":null,\"duration\":2,\"color\":{\"aM\":0}}],\"name\":\"jn_chuyin_gzhu08\"},{\"frame\":[{\"tweenEasing\":null,\"duration\":7,\"displayIndex\":-1},{\"tweenEasing\":null,\"duration\":1},{\"tweenEasing\":null,\"duration\":3,\"color\":{\"aM\":0}}],\"name\":\"jn_chuyin_gzhu07\"},{\"frame\":[{\"tweenEasing\":null,\"duration\":6,\"displayIndex\":-1},{\"tweenEasing\":null,\"duration\":1},{\"tweenEasing\":null,\"duration\":4,\"color\":{\"aM\":0}}],\"name\":\"jn_chuyin_gzhu06\"},{\"frame\":[{\"tweenEasing\":null,\"duration\":5,\"displayIndex\":-1},{\"tweenEasing\":null,\"duration\":1},{\"tweenEasing\":null,\"duration\":5,\"color\":{\"aM\":0}}],\"name\":\"jn_chuyin_gzhu05\"},{\"frame\":[{\"tweenEasing\":null,\"duration\":4,\"displayIndex\":-1},{\"tweenEasing\":null,\"duration\":1},{\"tweenEasing\":null,\"duration\":6,\"color\":{\"aM\":0}}],\"name\":\"jn_chuyin_gzhu04\"},{\"frame\":[{\"tweenEasing\":null,\"duration\":3,\"displayIndex\":-1},{\"tweenEasing\":null,\"duration\":1},{\"tweenEasing\":null,\"duration\":7,\"color\":{\"aM\":0}}],\"name\":\"jn_chuyin_gzhu03\"},{\"frame\":[{\"tweenEasing\":null,\"duration\":2,\"displayIndex\":-1},{\"tweenEasing\":null,\"duration\":1},{\"tweenEasing\":null,\"duration\":8,\"color\":{\"aM\":0}}],\"name\":\"jn_chuyin_gzhu02\"},{\"frame\":[{\"tweenEasing\":null,\"duration\":10,\"displayIndex\":-1},{\"tweenEasing\":null,\"duration\":1},{\"tweenEasing\":null,\"duration\":0,\"color\":{\"aM\":0}}],\"name\":\"jn_chuyin_gzhu010\"},{\"frame\":[{\"tweenEasing\":null,\"duration\":1,\"displayIndex\":-1},{\"tweenEasing\":null,\"duration\":1},{\"tweenEasing\":null,\"duration\":9,\"color\":{\"aM\":0}}],\"name\":\"jn_chuyin_gzhu01\"}],\"ik\":[],\"duration\":11,\"name\":\"jn_chuyin_gzhu\",\"ffd\":[]}],\"ik\":[],\"name\":\"jn_chuyin_gzhu\",\"aabb\":{\"width\":0,\"y\":0,\"height\":0,\"x\":0}}],\"name\":\"jn_chuyin_gzhu\",\"version\":\"4.5\"}"},{"__type__":"dragonBones.DragonBonesAtlasAsset","_name":"jn_chuyin_gzhu_tex","_atlasJson":"{\"imagePath\":\"jn_chuyin_gzhu_tex.png\",\"width\":512,\"height\":256,\"name\":\"jn_chuyin_gzhu\",\"SubTexture\":[{\"frameWidth\":89,\"y\":1,\"frameHeight\":106,\"frameY\":-4,\"width\":89,\"frameX\":0,\"height\":102,\"name\":\"jn_chuyin_gzhu010\",\"x\":183},{\"frameWidth\":89,\"y\":1,\"frameHeight\":106,\"frameY\":-5,\"width\":89,\"frameX\":0,\"height\":101,\"name\":\"jn_chuyin_gzhu09\",\"x\":274},{\"frameWidth\":89,\"y\":104,\"frameHeight\":106,\"frameY\":-6,\"width\":89,\"frameX\":0,\"height\":100,\"name\":\"jn_chuyin_gzhu08\",\"x\":274},{\"frameWidth\":89,\"y\":103,\"frameHeight\":106,\"frameY\":-8,\"width\":89,\"frameX\":0,\"height\":98,\"name\":\"jn_chuyin_gzhu07\",\"x\":365},{\"frameWidth\":89,\"y\":1,\"frameHeight\":106,\"frameY\":-6,\"width\":89,\"frameX\":0,\"height\":100,\"name\":\"jn_chuyin_gzhu06\",\"x\":365},{\"frameWidth\":89,\"y\":105,\"frameHeight\":106,\"frameY\":-5,\"width\":89,\"frameX\":0,\"height\":101,\"name\":\"jn_chuyin_gzhu05\",\"x\":183},{\"frameWidth\":89,\"y\":106,\"frameHeight\":106,\"frameY\":-4,\"width\":89,\"frameX\":0,\"height\":102,\"name\":\"jn_chuyin_gzhu04\",\"x\":92},{\"frameWidth\":89,\"y\":1,\"frameHeight\":106,\"frameY\":-3,\"width\":89,\"frameX\":0,\"height\":103,\"name\":\"jn_chuyin_gzhu03\",\"x\":92},{\"frameWidth\":89,\"y\":109,\"frameHeight\":106,\"frameY\":-1,\"width\":89,\"frameX\":0,\"height\":105,\"name\":\"jn_chuyin_gzhu02\",\"x\":1},{\"width\":89,\"y\":1,\"height\":106,\"name\":\"jn_chuyin_gzhu01\",\"x\":1}]}","texture":{"__uuid__":"69P6cZLqpMvKdQ5hCWOtkY"}}]
