[[{"__type__":"cc.Prefab","_name":"reinforceUnit","data":{"__id__":1},"asyncLoadAssets":null},{"__type__":"cc.Node","_name":"reinforceUnit_ske","_components":[{"__type__":"dragonBones.ArmatureDisplay","node":{"__id__":1},"_armatureName":"reinforceUnit","_N$dragonAsset":{"__uuid__":"12h5zIxhJOQbbOuhKA2tJi"},"_N$dragonAtlasAsset":{"__uuid__":"8eh2hCSGpNrZuNS2QQHOXR"}}],"_prefab":{"__type__":"cc.PrefabInfo","root":{"__id__":1},"asset":{"__id__":0},"fileId":"484995utjNFXoH1gblmyeeb"}}],{"__type__":"dragonBones.DragonBonesAsset","_name":"reinforceUnit_ske","_dragonBonesJson":"{\"frameRate\":30,\"armature\":[{\"aabb\":{\"width\":191.048,\"y\":-395.45,\"height\":487.9495,\"x\":-94.045},\"slot\":[{\"blendMode\":\"add\",\"parent\":\"lq1\",\"name\":\"lq1\",\"color\":{}},{\"blendMode\":\"add\",\"z\":1,\"parent\":\"lq12\",\"name\":\"lq12\",\"color\":{}},{\"blendMode\":\"add\",\"z\":2,\"parent\":\"lt1\",\"name\":\"lt1\",\"color\":{}},{\"blendMode\":\"add\",\"z\":3,\"parent\":\"l1\",\"name\":\"l1\",\"color\":{}},{\"blendMode\":\"add\",\"z\":4,\"parent\":\"l12\",\"name\":\"l12\",\"color\":{}},{\"blendMode\":\"add\",\"z\":5,\"parent\":\"diejia\",\"name\":\"diejia\",\"color\":{}}],\"type\":\"Armature\",\"frameRate\":30,\"defaultActions\":[{\"gotoAndPlay\":\"Skillup\"}],\"skin\":[{\"name\":\"\",\"slot\":[{\"display\":[{\"type\":\"image\",\"name\":\"texture_reinforceUnit/diejia\",\"transform\":{}}],\"blendMode\":\"add\",\"name\":\"diejia\"},{\"display\":[{\"type\":\"image\",\"name\":\"texture_reinforceUnit/lq1\",\"transform\":{\"y\":5.95,\"x\":3.05}}],\"blendMode\":\"add\",\"name\":\"lq1\"},{\"display\":[{\"type\":\"image\",\"name\":\"texture_reinforceUnit/lq1\",\"transform\":{\"y\":6.1,\"x\":3.05}}],\"blendMode\":\"add\",\"name\":\"lq12\"},{\"display\":[{\"type\":\"image\",\"name\":\"texture_reinforceUnit/l1\",\"transform\":{\"y\":-18.95}}],\"blendMode\":\"add\",\"name\":\"l12\"},{\"display\":[{\"type\":\"image\",\"name\":\"texture_reinforceUnit/lt1\",\"transform\":{\"x\":-0.5}}],\"blendMode\":\"add\",\"name\":\"lt1\"},{\"display\":[{\"type\":\"image\",\"name\":\"texture_reinforceUnit/l1\",\"transform\":{\"y\":-18.95}}],\"blendMode\":\"add\",\"name\":\"l1\"}]}],\"animation\":[{\"frame\":[],\"slot\":[{\"frame\":[{\"displayIndex\":-1,\"duration\":19,\"tweenEasing\":0,\"color\":{}},{\"duration\":38,\"tweenEasing\":0,\"color\":{}},{\"duration\":1,\"tweenEasing\":null,\"color\":{\"aM\":0}},{\"displayIndex\":-1,\"duration\":16,\"tweenEasing\":null,\"color\":{}}],\"name\":\"diejia\"},{\"frame\":[{\"displayIndex\":-1,\"duration\":23,\"tweenEasing\":0,\"color\":{}},{\"duration\":4,\"tweenEasing\":0,\"color\":{}},{\"duration\":1,\"tweenEasing\":null,\"color\":{\"aM\":0}},{\"displayIndex\":-1,\"duration\":46,\"tweenEasing\":null,\"color\":{}}],\"name\":\"l12\"},{\"frame\":[{\"displayIndex\":-1,\"duration\":21,\"tweenEasing\":0,\"color\":{}},{\"duration\":4,\"tweenEasing\":0,\"color\":{}},{\"duration\":1,\"tweenEasing\":null,\"color\":{\"aM\":0}},{\"displayIndex\":-1,\"duration\":48,\"tweenEasing\":null,\"color\":{}}],\"name\":\"l1\"},{\"frame\":[{\"duration\":5,\"tweenEasing\":0,\"color\":{}},{\"duration\":1,\"tweenEasing\":0,\"color\":{\"aM\":10}},{\"duration\":2,\"tweenEasing\":0,\"color\":{\"aM\":79}},{\"duration\":3,\"tweenEasing\":0,\"color\":{}},{\"duration\":3,\"tweenEasing\":0,\"color\":{}},{\"duration\":4,\"tweenEasing\":0,\"color\":{}},{\"duration\":3,\"tweenEasing\":0,\"color\":{}},{\"duration\":4,\"tweenEasing\":0,\"color\":{}},{\"duration\":1,\"tweenEasing\":null,\"color\":{\"aM\":0}},{\"displayIndex\":-1,\"duration\":48,\"tweenEasing\":null,\"color\":{}}],\"name\":\"lt1\"},{\"frame\":[{\"displayIndex\":-1,\"duration\":17,\"tweenEasing\":0,\"color\":{}},{\"duration\":7,\"tweenEasing\":0,\"color\":{\"aM\":0}},{\"duration\":13,\"tweenEasing\":0,\"color\":{}},{\"duration\":36,\"tweenEasing\":0,\"color\":{}},{\"duration\":1,\"tweenEasing\":null,\"color\":{\"aM\":0}},{\"displayIndex\":-1,\"duration\":0,\"tweenEasing\":null,\"color\":{}}],\"name\":\"lq12\"},{\"frame\":[{\"displayIndex\":-1,\"duration\":16,\"tweenEasing\":0,\"color\":{}},{\"duration\":7,\"tweenEasing\":0,\"color\":{\"aM\":0}},{\"duration\":10,\"tweenEasing\":0,\"color\":{}},{\"duration\":15,\"tweenEasing\":0,\"color\":{}},{\"duration\":1,\"tweenEasing\":null,\"color\":{\"aM\":0}},{\"displayIndex\":-1,\"duration\":25,\"tweenEasing\":null,\"color\":{}}],\"name\":\"lq1\"}],\"duration\":74,\"ffd\":[],\"name\":\"Skillup\",\"bone\":[{\"frame\":[{\"duration\":16,\"transform\":{\"y\":-2.25,\"scX\":2.1739,\"scY\":4.7619,\"x\":-1.6},\"tweenEasing\":0},{\"duration\":7,\"transform\":{},\"tweenEasing\":0},{\"duration\":10,\"transform\":{\"y\":-1.25,\"scX\":2.1739,\"scY\":2.1905,\"x\":-1.6},\"tweenEasing\":0},{\"duration\":15,\"transform\":{\"y\":6.05,\"scX\":4.7174,\"scY\":4.7619,\"x\":-5.1},\"tweenEasing\":0},{\"transform\":{\"y\":14.35,\"scX\":6.0217,\"scY\":6.0952,\"x\":-6.05},\"duration\":1,\"event\":\"fire\",\"tweenEasing\":null},{\"duration\":25,\"transform\":{\"y\":-2.25,\"scX\":2.1739,\"scY\":4.7619,\"x\":-1.6},\"tweenEasing\":null}],\"name\":\"lq1\"},{\"frame\":[{\"duration\":17,\"transform\":{\"y\":1.1,\"scX\":-1.6667,\"scY\":3.5714,\"x\":-4.8},\"tweenEasing\":0},{\"duration\":7,\"transform\":{},\"tweenEasing\":0},{\"duration\":13,\"transform\":{\"y\":-1.6,\"scX\":2.1667,\"scY\":2.1429,\"x\":2.1},\"tweenEasing\":0},{\"duration\":36,\"transform\":{\"y\":7.9,\"scX\":4.7,\"scY\":4.6429,\"x\":6.65},\"tweenEasing\":0},{\"duration\":1,\"transform\":{\"y\":17.8,\"scX\":6.6333,\"scY\":6.5714,\"x\":5.65},\"tweenEasing\":null},{\"duration\":0,\"transform\":{\"y\":1.1,\"scX\":-1.6667,\"scY\":3.5714,\"x\":-4.8},\"tweenEasing\":null}],\"name\":\"lq12\"},{\"frame\":[{\"duration\":5,\"transform\":{},\"tweenEasing\":0},{\"duration\":1,\"transform\":{\"scX\":5.4444},\"tweenEasing\":0},{\"duration\":2,\"transform\":{\"scX\":7.8889},\"tweenEasing\":0},{\"duration\":3,\"transform\":{\"scX\":3.4444},\"tweenEasing\":0},{\"duration\":3,\"transform\":{\"scX\":7.8889},\"tweenEasing\":0},{\"duration\":4,\"transform\":{\"scX\":3.4444},\"tweenEasing\":0},{\"duration\":3,\"transform\":{\"y\":-16,\"scX\":8.2222,\"scY\":1.0998},\"tweenEasing\":0},{\"duration\":4,\"transform\":{\"y\":-76.9,\"scX\":2.6667,\"scY\":1.2524},\"tweenEasing\":0},{\"duration\":1,\"transform\":{\"y\":236.45,\"scX\":0.8889,\"scY\":0.3386},\"tweenEasing\":null},{\"duration\":48,\"transform\":{\"y\":325.45,\"scX\":11.1111,\"scY\":0.1957},\"tweenEasing\":null}],\"name\":\"lt1\"},{\"frame\":[{\"duration\":21,\"transform\":{\"y\":-2.55,\"scX\":0.6536,\"x\":0.5},\"tweenEasing\":0},{\"duration\":4,\"transform\":{},\"tweenEasing\":0},{\"duration\":1,\"transform\":{\"scX\":1.9477,\"scY\":2.45},\"tweenEasing\":null},{\"duration\":48,\"transform\":{\"y\":-2.55,\"scX\":0.6536,\"x\":0.5},\"tweenEasing\":null}],\"name\":\"l1\"},{\"frame\":[{\"duration\":23,\"transform\":{\"y\":-12.4,\"scX\":0.4831,\"scY\":1.7857,\"x\":0.5},\"tweenEasing\":0},{\"duration\":4,\"transform\":{},\"tweenEasing\":0},{\"duration\":1,\"transform\":{\"scX\":1.9469,\"scY\":2.4286},\"tweenEasing\":null},{\"duration\":46,\"transform\":{\"y\":-12.4,\"scX\":0.4831,\"scY\":1.7857,\"x\":0.5},\"tweenEasing\":null}],\"name\":\"l12\"},{\"frame\":[{\"duration\":19,\"transform\":{\"y\":24,\"scX\":0.3817,\"scY\":0.4202,\"x\":1.05},\"tweenEasing\":0},{\"duration\":38,\"transform\":{},\"tweenEasing\":0},{\"duration\":1,\"transform\":{\"y\":40,\"scX\":2.229,\"scY\":1.395,\"x\":10},\"tweenEasing\":null},{\"duration\":16,\"transform\":{\"y\":24,\"scX\":0.3817,\"scY\":0.4202,\"x\":1.05},\"tweenEasing\":null}],\"name\":\"diejia\"},{\"frame\":[{\"duration\":74,\"transform\":{},\"tweenEasing\":null}],\"name\":\"root\"}]}],\"ik\":[],\"name\":\"reinforceUnit\",\"bone\":[{\"name\":\"root\",\"transform\":{}},{\"transform\":{\"y\":2.55,\"scX\":1.53,\"x\":-0.5},\"name\":\"l1\",\"parent\":\"root\"},{\"transform\":{\"y\":-1.1,\"scX\":-0.6,\"scY\":0.28,\"x\":4.8},\"name\":\"lq12\",\"parent\":\"root\"},{\"transform\":{\"y\":-325.45,\"scX\":0.09,\"scY\":5.11},\"name\":\"lt1\",\"parent\":\"root\"},{\"transform\":{\"y\":2.25,\"scX\":0.46,\"scY\":0.21,\"x\":1.6},\"name\":\"lq1\",\"parent\":\"root\"},{\"transform\":{\"y\":12.4,\"scX\":2.07,\"scY\":0.56,\"x\":-0.5},\"name\":\"l12\",\"parent\":\"root\"},{\"transform\":{\"y\":-24,\"scX\":2.62,\"scY\":2.38,\"x\":-1.05},\"name\":\"diejia\",\"parent\":\"root\"}]}],\"name\":\"reinforceUnit\",\"version\":\"4.5\",\"isGlobal\":0}"},{"__type__":"dragonBones.DragonBonesAtlasAsset","_name":"reinforceUnit_tex","_atlasJson":"{\"name\":\"reinforceUnit\",\"SubTexture\":[{\"frameHeight\":178,\"y\":1,\"frameWidth\":188,\"frameX\":-9,\"width\":177,\"frameY\":-4,\"height\":172,\"name\":\"texture_reinforceUnit/lq1\",\"x\":1},{\"frameHeight\":140,\"y\":175,\"frameWidth\":188,\"frameX\":-3,\"width\":182,\"frameY\":-5,\"height\":135,\"name\":\"texture_reinforceUnit/lt1\",\"x\":1},{\"width\":109,\"y\":312,\"height\":78,\"name\":\"texture_reinforceUnit/l1\",\"x\":1},{\"frameHeight\":74,\"y\":1,\"frameWidth\":74,\"frameX\":-2,\"width\":71,\"frameY\":-2,\"height\":71,\"name\":\"texture_reinforceUnit/diejia\",\"x\":180}],\"imagePath\":\"reinforceUnit_tex.png\"}","texture":{"__uuid__":"ean6hcb0BGl7kcHnlxRtjF"}}]
