[{"__type__":"dragonBones.DragonBonesAsset","_name":"taishiciSkill12_ske","_dragonBonesJson":"{\"frameRate\":30,\"armature\":[{\"aabb\":{\"width\":165.7070555984974,\"y\":-85.42480022445321,\"height\":160.40460044890642,\"x\":-98.5415277992487},\"slot\":[{\"name\":\"kuosan\",\"parent\":\"kuosan\",\"color\":{}},{\"z\":1,\"name\":\"qqqq\",\"parent\":\"qqqq\",\"color\":{}},{\"z\":2,\"name\":\"guaiguang\",\"parent\":\"guaiguang\",\"color\":{}},{\"z\":3,\"name\":\"heidian\",\"parent\":\"heidian\",\"color\":{}},{\"z\":4,\"name\":\"fendian\",\"parent\":\"fendian\",\"color\":{}}],\"type\":\"Armature\",\"frameRate\":30,\"defaultActions\":[{\"gotoAndPlay\":\"taishiciSkill12\"}],\"skin\":[{\"name\":\"\",\"slot\":[{\"display\":[{\"type\":\"image\",\"name\":\"texture_taishiciSkill12/guaiguang\",\"transform\":{}}],\"name\":\"guaiguang\"},{\"display\":[{\"type\":\"image\",\"name\":\"texture_taishiciSkill12/kuosan\",\"transform\":{\"y\":1.65,\"x\":1.1}}],\"name\":\"kuosan\"},{\"display\":[{\"type\":\"image\",\"name\":\"texture_taishiciSkill12/fendian\",\"transform\":{\"y\":1.7,\"x\":1.7}}],\"name\":\"fendian\"},{\"display\":[{\"filterType\":null,\"type\":\"armature\",\"name\":\"texture_taishiciSkill12/qqqq\",\"transform\":{\"y\":-70.25,\"x\":-72.9}}],\"name\":\"qqqq\"},{\"display\":[{\"type\":\"image\",\"name\":\"texture_taishiciSkill12/heidian\",\"transform\":{\"x\":0.45}}],\"name\":\"heidian\"}]}],\"animation\":[{\"frame\":[],\"slot\":[{\"frame\":[{\"duration\":10,\"tweenEasing\":0,\"color\":{}},{\"duration\":18,\"tweenEasing\":0,\"color\":{}},{\"duration\":1,\"tweenEasing\":null,\"color\":{\"aM\":0}},{\"displayIndex\":-1,\"duration\":25,\"tweenEasing\":null,\"color\":{}}],\"name\":\"fendian\"},{\"frame\":[{\"duration\":6,\"tweenEasing\":0,\"color\":{}},{\"duration\":20,\"tweenEasing\":0,\"color\":{}},{\"duration\":1,\"tweenEasing\":null,\"color\":{\"aM\":0}},{\"displayIndex\":-1,\"duration\":27,\"tweenEasing\":null,\"color\":{}}],\"name\":\"heidian\"},{\"frame\":[{\"duration\":9,\"tweenEasing\":0,\"color\":{}},{\"duration\":19,\"tweenEasing\":0,\"color\":{\"aM\":35}},{\"duration\":1,\"tweenEasing\":null,\"color\":{\"aM\":0}},{\"displayIndex\":-1,\"duration\":25,\"tweenEasing\":null,\"color\":{}}],\"name\":\"guaiguang\"},{\"frame\":[{\"displayIndex\":-1,\"duration\":4,\"tweenEasing\":0,\"color\":{}},{\"duration\":3,\"tweenEasing\":0,\"color\":{\"aM\":0}},{\"duration\":22,\"tweenEasing\":0,\"color\":{}},{\"duration\":24,\"tweenEasing\":0,\"color\":{}},{\"duration\":1,\"tweenEasing\":null,\"color\":{\"aM\":0}},{\"displayIndex\":-1,\"duration\":0,\"tweenEasing\":null,\"color\":{}}],\"name\":\"qqqq\"},{\"frame\":[{\"displayIndex\":-1,\"duration\":12,\"tweenEasing\":0,\"color\":{}},{\"duration\":15,\"tweenEasing\":0,\"color\":{\"aM\":0}},{\"duration\":23,\"tweenEasing\":0,\"color\":{}},{\"duration\":1,\"tweenEasing\":null,\"color\":{\"aM\":0}},{\"displayIndex\":-1,\"duration\":3,\"tweenEasing\":null,\"color\":{}}],\"name\":\"kuosan\"}],\"duration\":54,\"ffd\":[],\"name\":\"taishiciSkill12\",\"bone\":[{\"frame\":[{\"duration\":12,\"transform\":{\"y\":-1.9,\"scX\":0.7042,\"scY\":1.6949,\"x\":-0.7},\"tweenEasing\":0},{\"duration\":15,\"transform\":{},\"tweenEasing\":0},{\"duration\":23,\"transform\":{\"scX\":1.4789,\"scY\":1.4746,\"x\":0.05},\"tweenEasing\":0},{\"duration\":1,\"transform\":{\"scX\":1.7113,\"scY\":1.7119},\"tweenEasing\":null},{\"duration\":3,\"transform\":{\"y\":-1.9,\"scX\":0.7042,\"scY\":1.6949,\"x\":-0.7},\"tweenEasing\":null}],\"name\":\"kuosan\"},{\"frame\":[{\"duration\":4,\"transform\":{\"y\":-1.1,\"scX\":4.5455,\"scY\":11.1111,\"x\":-0.35},\"tweenEasing\":0},{\"duration\":3,\"transform\":{},\"tweenEasing\":0},{\"duration\":22,\"transform\":{\"scX\":1.9091,\"scY\":1.8889},\"tweenEasing\":0},{\"duration\":24,\"transform\":{\"scX\":3.5909,\"scY\":3.6667},\"tweenEasing\":0},{\"duration\":1,\"transform\":{\"scX\":4.8636,\"scY\":4.8889},\"tweenEasing\":null},{\"duration\":0,\"transform\":{\"y\":-1.1,\"scX\":4.5455,\"scY\":11.1111,\"x\":-0.35},\"tweenEasing\":null}],\"name\":\"qqqq\"},{\"frame\":[{\"duration\":9,\"transform\":{},\"tweenEasing\":0},{\"duration\":19,\"transform\":{\"y\":1.95,\"scX\":2.54,\"scY\":2.5854},\"tweenEasing\":0},{\"duration\":1,\"transform\":{\"y\":2.95,\"scX\":3.38,\"scY\":3.4146},\"tweenEasing\":null},{\"duration\":25,\"transform\":{\"y\":-1.9,\"scY\":2.439,\"x\":-0.25},\"tweenEasing\":null}],\"name\":\"guaiguang\"},{\"frame\":[{\"duration\":6,\"transform\":{},\"tweenEasing\":0},{\"transform\":{\"y\":-0.55,\"scX\":2.78,\"scY\":2.4677,\"x\":0.6},\"duration\":20,\"event\":\"fire\",\"tweenEasing\":0},{\"duration\":1,\"transform\":{\"y\":-2.05,\"scX\":2.34,\"scY\":2.0645,\"x\":0.85},\"tweenEasing\":null},{\"duration\":27,\"transform\":{\"y\":-0.2,\"scX\":0.6667,\"scY\":1.6129,\"x\":-0.25},\"tweenEasing\":null}],\"name\":\"heidian\"},{\"frame\":[{\"duration\":10,\"transform\":{},\"tweenEasing\":0},{\"duration\":18,\"transform\":{\"scX\":8.0926,\"scY\":8.2727,\"x\":-0.75},\"tweenEasing\":0},{\"duration\":1,\"transform\":{\"y\":-0.05,\"scX\":6.3148,\"scY\":6.4545,\"x\":-0.8},\"tweenEasing\":null},{\"duration\":25,\"transform\":{\"y\":0.45,\"scX\":1.8519,\"scY\":4.5455,\"x\":-0.05},\"tweenEasing\":null}],\"name\":\"fendian\"},{\"frame\":[{\"duration\":54,\"transform\":{},\"tweenEasing\":null}],\"name\":\"root\"}]}],\"ik\":[],\"name\":\"taishiciSkill12\",\"bone\":[{\"name\":\"root\",\"transform\":{}},{\"transform\":{\"y\":1.9,\"scY\":0.41,\"x\":0.25},\"name\":\"guaiguang\",\"parent\":\"root\"},{\"transform\":{\"y\":1.1,\"scX\":0.22,\"scY\":0.09,\"x\":0.35},\"name\":\"qqqq\",\"parent\":\"root\"},{\"transform\":{\"y\":1.9,\"scX\":1.42,\"scY\":0.59,\"x\":0.7},\"name\":\"kuosan\",\"parent\":\"root\"},{\"transform\":{\"y\":0.2,\"scX\":1.5,\"scY\":0.62,\"x\":0.25},\"name\":\"heidian\",\"parent\":\"root\"},{\"transform\":{\"y\":-0.45,\"scX\":0.54,\"scY\":0.22,\"x\":0.05},\"name\":\"fendian\",\"parent\":\"root\"}]},{\"aabb\":{\"width\":79,\"y\":36.19999999999999,\"height\":76,\"x\":37.749999999999986},\"slot\":[{\"name\":\"qqq\",\"parent\":\"qqq\",\"color\":{}}],\"type\":\"Armature\",\"frameRate\":30,\"defaultActions\":[{\"gotoAndPlay\":\"unnamed\"}],\"skin\":[{\"name\":\"\",\"slot\":[{\"display\":[{\"type\":\"image\",\"name\":\"texture_taishiciSkill12/qqq\",\"transform\":{\"y\":2.1,\"x\":2.15}}],\"name\":\"qqq\"}]}],\"animation\":[{\"frame\":[],\"slot\":[{\"frame\":[{\"duration\":29,\"tweenEasing\":0,\"color\":{}},{\"duration\":0,\"tweenEasing\":null,\"color\":{}}],\"name\":\"qqq\"}],\"duration\":29,\"ffd\":[],\"name\":\"unnamed\",\"bone\":[{\"frame\":[{\"duration\":29,\"transform\":{},\"tweenEasing\":0,\"tweenRotate\":1},{\"duration\":0,\"transform\":{\"skX\":91.05,\"skY\":91.05,\"scX\":0.93,\"x\":0.05},\"tweenEasing\":null}],\"name\":\"qqq\"}]}],\"ik\":[],\"name\":\"texture_taishiciSkill12/qqqq\",\"bone\":[{\"name\":\"qqq\",\"transform\":{\"y\":70,\"scX\":2,\"scY\":2,\"x\":72.95}}]}],\"name\":\"taishiciSkill12\",\"version\":\"4.5\",\"isGlobal\":0}"},{"__type__":"dragonBones.DragonBonesAtlasAsset","_name":"taishiciSkill12_tex","_atlasJson":"{\"name\":\"taishiciSkill12\",\"SubTexture\":[{\"frameHeight\":93,\"y\":1,\"frameWidth\":93,\"frameX\":-3,\"width\":85,\"frameY\":-3,\"height\":85,\"name\":\"texture_taishiciSkill12/kuosan\",\"x\":1},{\"frameHeight\":59,\"y\":1,\"frameWidth\":59,\"frameX\":-1,\"width\":58,\"frameY\":-1,\"height\":58,\"name\":\"texture_taishiciSkill12/guaiguang\",\"x\":167},{\"frameHeight\":18,\"y\":31,\"frameWidth\":17,\"frameX\":-1,\"width\":15,\"frameY\":-1,\"height\":16,\"name\":\"texture_taishiciSkill12/heidian\",\"x\":227},{\"frameHeight\":43,\"y\":1,\"frameWidth\":43,\"frameX\":-7,\"width\":27,\"frameY\":-6,\"height\":28,\"name\":\"texture_taishiciSkill12/fendian\",\"x\":227},{\"frameHeight\":76,\"y\":1,\"frameWidth\":79,\"frameX\":0,\"width\":77,\"frameY\":0,\"height\":74,\"name\":\"texture_taishiciSkill12/qqq\",\"x\":88}],\"imagePath\":\"taishiciSkill12_tex.png\"}","texture":{"__uuid__":"afCiF+tWdHTJTRRnceOO6i"}},[{"__type__":"cc.Prefab","_name":"taishiciSkill12","data":{"__id__":1},"asyncLoadAssets":null},{"__type__":"cc.Node","_name":"taishiciSkill12_ske","_components":[{"__type__":"dragonBones.ArmatureDisplay","node":{"__id__":1},"_armatureName":"taishiciSkill12","_N$dragonAsset":{"__uuid__":"9bxHzwrQ9Cg5kuG/19LMIn"},"_N$dragonAtlasAsset":{"__uuid__":"c0E6R89qBOha/uF8G7th1S"}}],"_prefab":{"__type__":"cc.PrefabInfo","root":{"__id__":1},"asset":{"__id__":0},"fileId":"78ad0p8vwRP7LYoWO+1CcPP"}}]]
