[{"__type__":"dragonBones.DragonBonesAsset","_name":"rotatelight_ske","_dragonBonesJson":"{\"frameRate\":30,\"isGlobal\":0,\"armature\":[{\"animation\":[{\"ffd\":[],\"frame\":[],\"slot\":[{\"frame\":[{\"tweenEasing\":0,\"duration\":1,\"color\":{}},{\"tweenEasing\":0,\"duration\":4,\"color\":{}},{\"tweenEasing\":0,\"duration\":28,\"color\":{}},{\"tweenEasing\":0,\"duration\":1,\"color\":{\"aM\":0}},{\"tweenEasing\":null,\"displayIndex\":-1,\"duration\":0,\"color\":{}}],\"name\":\"sweep\"}],\"bone\":[{\"frame\":[{\"tweenEasing\":0,\"transform\":{},\"duration\":1},{\"tweenEasing\":0,\"transform\":{\"scX\":1.22,\"scY\":1.2222,\"x\":-0.05},\"duration\":4},{\"tweenEasing\":0,\"transform\":{\"scX\":1.1067,\"scY\":1.1111},\"duration\":28},{\"tweenEasing\":0,\"transform\":{\"scX\":1.1067,\"scY\":1.1111},\"duration\":1},{\"tweenEasing\":null,\"transform\":{\"y\":-0.15,\"scX\":0.6667,\"scY\":1.1111,\"x\":-7.2},\"duration\":0}],\"name\":\"sweep\"}],\"name\":\"action1\",\"duration\":34}],\"type\":\"Armature\",\"name\":\"rotatelight\",\"defaultActions\":[{\"gotoAndPlay\":\"action1\"}],\"ik\":[],\"bone\":[{\"name\":\"sweep\",\"transform\":{\"y\":0.15,\"scX\":1.5,\"scY\":0.9,\"x\":7.2}}],\"skin\":[{\"name\":\"\",\"slot\":[{\"display\":[{\"filterType\":null,\"type\":\"armature\",\"name\":\"texture_rotatelight/sweep\",\"transform\":{\"y\":-1.5,\"x\":-4.8}}],\"name\":\"sweep\"}]}],\"aabb\":{\"width\":214.66062023490667,\"y\":-88.95399338826537,\"height\":175.50798677653074,\"x\":-107.33031011745334},\"frameRate\":30,\"slot\":[{\"name\":\"sweep\",\"parent\":\"sweep\",\"color\":{}}]},{\"animation\":[{\"ffd\":[],\"frame\":[],\"slot\":[{\"frame\":[{\"tweenEasing\":0,\"displayIndex\":-1,\"duration\":24,\"color\":{}},{\"tweenEasing\":0,\"duration\":24,\"color\":{\"aM\":0}},{\"tweenEasing\":0,\"duration\":55,\"color\":{}},{\"tweenEasing\":null,\"duration\":161,\"color\":{\"aM\":0}}],\"name\":\"lights4\"},{\"frame\":[{\"tweenEasing\":0,\"duration\":11,\"color\":{\"aM\":54}},{\"tweenEasing\":0,\"duration\":55,\"color\":{}},{\"tweenEasing\":0,\"duration\":1,\"color\":{\"aM\":0}},{\"tweenEasing\":0,\"displayIndex\":-1,\"duration\":24,\"color\":{}},{\"tweenEasing\":0,\"duration\":12,\"color\":{\"aM\":0}},{\"tweenEasing\":0,\"duration\":1,\"color\":{\"aM\":50}},{\"tweenEasing\":null,\"displayIndex\":-1,\"duration\":160,\"color\":{}}],\"name\":\"lights3\"},{\"frame\":[{\"tweenEasing\":0,\"duration\":20,\"color\":{\"aM\":36}},{\"tweenEasing\":0,\"duration\":1,\"color\":{\"aM\":0}},{\"tweenEasing\":0,\"displayIndex\":-1,\"duration\":24,\"color\":{}},{\"tweenEasing\":0,\"duration\":24,\"color\":{\"aM\":0}},{\"tweenEasing\":0,\"duration\":34,\"color\":{}},{\"tweenEasing\":0,\"duration\":1,\"color\":{\"aM\":38}},{\"tweenEasing\":null,\"displayIndex\":-1,\"duration\":160,\"color\":{}}],\"name\":\"lights2\"},{\"frame\":[{\"tweenEasing\":0,\"duration\":24,\"color\":{\"aM\":0}},{\"tweenEasing\":0,\"duration\":55,\"color\":{}},{\"tweenEasing\":0,\"duration\":1,\"color\":{\"aM\":0}},{\"tweenEasing\":null,\"displayIndex\":-1,\"duration\":184,\"color\":{}}],\"name\":\"lights\"}],\"bone\":[{\"frame\":[{\"tweenEasing\":0,\"transform\":{},\"duration\":24},{\"tweenEasing\":0,\"transform\":{\"skX\":-0.67,\"skY\":-0.67,\"scX\":1.0326,\"scY\":1.0326},\"duration\":55},{\"tweenEasing\":0,\"transform\":{\"skX\":-1.95,\"skY\":-1.95,\"scX\":1.087,\"scY\":1.087},\"duration\":1},{\"tweenEasing\":null,\"transform\":{\"skX\":-1.95,\"skY\":-1.95,\"scX\":1.087,\"scY\":1.087},\"duration\":184}],\"name\":\"lights\"},{\"frame\":[{\"tweenEasing\":0,\"transform\":{},\"duration\":20},{\"tweenEasing\":0,\"transform\":{\"skX\":0.3,\"skY\":0.3,\"scX\":1.0227,\"scY\":1.0227,\"x\":-0.05},\"duration\":1},{\"tweenEasing\":0,\"transform\":{\"y\":-0.1,\"skX\":0.3,\"skY\":0.3,\"scX\":-1.1364,\"scY\":1.1364,\"x\":0.1},\"duration\":24},{\"tweenEasing\":0,\"transform\":{\"skX\":-1.65,\"skY\":-1.65,\"scX\":0.9432,\"scY\":0.9432,\"x\":-0.05},\"duration\":24},{\"tweenEasing\":0,\"transform\":{\"skX\":-0.98,\"skY\":-0.98,\"scX\":0.9659,\"scY\":0.9659,\"x\":-0.05},\"duration\":34},{\"tweenEasing\":0,\"transform\":{\"skX\":-0.01,\"skY\":-0.01},\"duration\":1},{\"tweenEasing\":null,\"transform\":{\"y\":-0.1,\"skX\":0.3,\"skY\":0.3,\"scX\":-1.1364,\"scY\":1.1364,\"x\":0.1},\"duration\":160}],\"name\":\"lights2\"},{\"frame\":[{\"tweenEasing\":0,\"transform\":{},\"duration\":11},{\"tweenEasing\":0,\"transform\":{\"skX\":-0.24,\"skY\":-0.24,\"scX\":1.0119,\"scY\":1.0119},\"duration\":55},{\"tweenEasing\":0,\"transform\":{\"skX\":-1.52,\"skY\":-1.52,\"scX\":1.0714,\"scY\":1.0714},\"duration\":1},{\"tweenEasing\":0,\"transform\":{\"y\":-0.1,\"skX\":-1.52,\"skY\":-1.52,\"scX\":1.1905,\"scY\":1.1905,\"x\":-0.35},\"duration\":24},{\"tweenEasing\":0,\"transform\":{\"skX\":0.43,\"skY\":0.43,\"scX\":0.9881,\"scY\":0.9881},\"duration\":12},{\"tweenEasing\":0,\"transform\":{\"skX\":0.01,\"skY\":0.01},\"duration\":1},{\"tweenEasing\":null,\"transform\":{\"y\":-0.1,\"skX\":-1.52,\"skY\":-1.52,\"scX\":1.1905,\"scY\":1.1905,\"x\":-0.35},\"duration\":160}],\"name\":\"lights3\"},{\"frame\":[{\"tweenEasing\":0,\"transform\":{\"y\":-0.4,\"skX\":-18.18,\"skY\":-18.18,\"scX\":0.8772,\"scY\":0.8772,\"x\":0.1},\"duration\":24},{\"tweenEasing\":0,\"transform\":{},\"duration\":24},{\"tweenEasing\":0,\"transform\":{\"skX\":-0.67,\"skY\":-0.67,\"scX\":1.0263,\"scY\":1.0263},\"duration\":55},{\"tweenEasing\":null,\"transform\":{\"skX\":-1.95,\"skY\":-1.95,\"scX\":1.0877,\"scY\":1.0877},\"duration\":161}],\"name\":\"lights4\"},{\"frame\":[{\"tweenEasing\":null,\"transform\":{},\"duration\":264}],\"name\":\"root\"}],\"name\":\"unnamed\",\"duration\":264}],\"type\":\"Armature\",\"name\":\"texture_rotatelight/sweep\",\"defaultActions\":[{\"gotoAndPlay\":\"unnamed\"}],\"ik\":[],\"bone\":[{\"name\":\"root\",\"transform\":{}},{\"transform\":{\"y\":0.1,\"skX\":1.52,\"skY\":1.52,\"scX\":0.84,\"scY\":0.84,\"x\":0.35},\"name\":\"lights3\",\"parent\":\"root\"},{\"transform\":{\"y\":0.1,\"skX\":-0.3,\"skY\":-0.3,\"scX\":-0.88,\"scY\":0.88,\"x\":-0.1},\"name\":\"lights2\",\"parent\":\"root\"},{\"transform\":{\"skX\":1.95,\"skY\":1.95,\"scX\":0.92,\"scY\":0.92},\"name\":\"lights\",\"parent\":\"root\"},{\"transform\":{\"y\":0.4,\"skX\":18.18,\"skY\":18.18,\"scX\":1.14,\"scY\":1.14,\"x\":-0.1},\"name\":\"lights4\",\"parent\":\"root\"}],\"skin\":[{\"name\":\"\",\"slot\":[{\"display\":[{\"type\":\"image\",\"name\":\"texture_rotatelight/lights\",\"transform\":{\"y\":1.25,\"x\":2.75}}],\"blendMode\":\"add\",\"name\":\"lights4\"},{\"display\":[{\"type\":\"image\",\"name\":\"texture_rotatelight/lights\",\"transform\":{\"y\":1.25,\"x\":2.75}}],\"blendMode\":\"add\",\"name\":\"lights2\"},{\"display\":[{\"type\":\"image\",\"name\":\"texture_rotatelight/lights\",\"transform\":{\"y\":1.25,\"x\":2.75}}],\"blendMode\":\"add\",\"name\":\"lights3\"},{\"display\":[{\"type\":\"image\",\"name\":\"texture_rotatelight/lights\",\"transform\":{\"y\":1.25,\"x\":2.75}}],\"blendMode\":\"add\",\"name\":\"lights\"}]}],\"aabb\":{\"width\":232.14554225187004,\"y\":-90.2890946543839,\"height\":184.52109044172067,\"x\":-116.0142072670242},\"frameRate\":30,\"slot\":[{\"blendMode\":\"add\",\"parent\":\"lights\",\"name\":\"lights\",\"color\":{}},{\"blendMode\":\"add\",\"z\":1,\"parent\":\"lights2\",\"name\":\"lights2\",\"color\":{}},{\"blendMode\":\"add\",\"z\":2,\"parent\":\"lights3\",\"name\":\"lights3\",\"color\":{}},{\"blendMode\":\"add\",\"z\":3,\"parent\":\"lights4\",\"name\":\"lights4\",\"color\":{}}]}],\"name\":\"rotatelight\",\"version\":\"4.5\"}"},{"__type__":"dragonBones.DragonBonesAtlasAsset","_name":"rotatelight_tex","_atlasJson":"{\"SubTexture\":[{\"frameY\":-6,\"y\":1,\"frameWidth\":227,\"frameHeight\":183,\"width\":187,\"height\":170,\"name\":\"texture_rotatelight/lights\",\"frameX\":-19,\"x\":1}],\"imagePath\":\"rotatelight_tex.png\",\"name\":\"rotatelight\"}","texture":{"__uuid__":"02JXGsRWFEwpUzdKWGyXFb"}},[{"__type__":"cc.Prefab","_name":"rotatelight","data":{"__id__":1},"asyncLoadAssets":null},{"__type__":"cc.Node","_name":"rotatelight","_components":[{"__type__":"dragonBones.ArmatureDisplay","node":{"__id__":1},"_armatureName":"rotatelight","_N$dragonAsset":{"__uuid__":"b1afjd13VDS6xlGptVpQhh"},"_N$dragonAtlasAsset":{"__uuid__":"b5aHfDkP9DKYncTg/rqPmQ"}}],"_prefab":{"__type__":"cc.PrefabInfo","root":{"__id__":1},"asset":{"__id__":0},"fileId":"1c2e3/rHttHArbWEZfW8J+7"}}]]
