[{"__type__":"dragonBones.DragonBonesAtlasAsset","_name":"skillactive_tex","_atlasJson":"{\"name\":\"skillactive\",\"SubTexture\":[{\"width\":80,\"y\":102,\"height\":80,\"name\":\"texture_skillactive/q1\",\"x\":1},{\"width\":17,\"y\":216,\"height\":17,\"name\":\"texture_skillactive/liqsli\",\"x\":48},{\"frameHeight\":100,\"y\":1,\"frameWidth\":91,\"frameX\":0,\"width\":91,\"frameY\":0,\"height\":99,\"name\":\"texture_skillactive/ddd\",\"x\":1},{\"width\":45,\"y\":184,\"height\":49,\"name\":\"texture_skillactive/quanquan2\",\"x\":1},{\"width\":19,\"y\":184,\"height\":30,\"name\":\"texture_skillactive/quanquan3\",\"x\":48},{\"frameHeight\":74,\"y\":102,\"frameWidth\":76,\"frameX\":-4,\"width\":69,\"frameY\":-1,\"height\":72,\"name\":\"texture_skillactive/quanquan\",\"x\":83},{\"frameHeight\":64,\"y\":176,\"frameWidth\":64,\"frameX\":-4,\"width\":57,\"frameY\":-4,\"height\":57,\"name\":\"texture_skillactive/111\",\"x\":83}],\"imagePath\":\"skillactive_tex.png\"}","texture":{"__uuid__":"f4bbhSytxPJJ0G2KXH/zFw"}},[{"__type__":"cc.Prefab","_name":"skillactive","data":{"__id__":1},"asyncLoadAssets":null},{"__type__":"cc.Node","_name":"skillactive_ske","_components":[{"__type__":"dragonBones.ArmatureDisplay","node":{"__id__":1},"_armatureName":"skillactive","_N$dragonAsset":{"__uuid__":"84cX5auwlL7JQUQEV/ytIV"},"_N$dragonAtlasAsset":{"__uuid__":"4fsjqh+ItLp7LFpaex9ImY"}}],"_prefab":{"__type__":"cc.PrefabInfo","root":{"__id__":1},"asset":{"__id__":0},"fileId":"8f5075UvBBCApHiDQj+uOVR"}}],{"__type__":"dragonBones.DragonBonesAsset","_name":"skillactive_ske","_dragonBonesJson":"{\"frameRate\":30,\"armature\":[{\"aabb\":{\"width\":92.8041719371972,\"y\":-48.35,\"height\":101.81796280564946,\"x\":-44.3541719371972},\"slot\":[{\"name\":\"q1\",\"parent\":\"q1\",\"color\":{}},{\"z\":1,\"name\":\"liqsli\",\"parent\":\"liqsli\",\"color\":{}},{\"blendMode\":\"add\",\"z\":2,\"parent\":\"ddd\",\"name\":\"ddd\",\"color\":{}},{\"z\":3,\"name\":\"quanquan2\",\"parent\":\"quanquan2\",\"color\":{}},{\"z\":4,\"name\":\"quanquan3\",\"parent\":\"quanquan3\",\"color\":{}},{\"blendMode\":\"add\",\"z\":5,\"parent\":\"quanquan\",\"name\":\"quanquan\",\"color\":{}},{\"z\":6,\"name\":\"liqsli_1\",\"parent\":\"liqsli_1\",\"color\":{}},{\"z\":7,\"name\":\"ddd_1\",\"parent\":\"ddd_1\",\"color\":{}},{\"z\":8,\"name\":\"quanquan2_1\",\"parent\":\"quanquan2_1\",\"color\":{}},{\"blendMode\":\"add\",\"z\":9,\"parent\":\"quanquan_1\",\"name\":\"quanquan_1\",\"color\":{}},{\"blendMode\":\"add\",\"z\":10,\"parent\":\"111_1\",\"name\":\"111_1\",\"color\":{}}],\"type\":\"Armature\",\"frameRate\":30,\"defaultActions\":[{\"gotoAndPlay\":\"skillactive\"}],\"skin\":[{\"name\":\"\",\"slot\":[{\"display\":[{\"type\":\"image\",\"name\":\"texture_skillactive/111\",\"transform\":{\"y\":0.4,\"x\":0.4}}],\"blendMode\":\"add\",\"name\":\"111_1\"},{\"display\":[{\"type\":\"image\",\"name\":\"texture_skillactive/ddd\",\"transform\":{\"y\":0.5,\"x\":0.25}}],\"name\":\"ddd_1\"},{\"display\":[{\"type\":\"image\",\"name\":\"texture_skillactive/ddd\",\"transform\":{\"y\":0.5,\"x\":0.25}}],\"blendMode\":\"add\",\"name\":\"ddd\"},{\"display\":[{\"type\":\"image\",\"name\":\"texture_skillactive/quanquan2\",\"transform\":{\"y\":1.35,\"x\":0.25}}],\"name\":\"quanquan2_1\"},{\"display\":[{\"type\":\"image\",\"name\":\"texture_skillactive/quanquan2\",\"transform\":{\"y\":1.35,\"x\":0.2}}],\"name\":\"quanquan2\"},{\"display\":[{\"type\":\"image\",\"name\":\"texture_skillactive/quanquan3\",\"transform\":{\"y\":-0.65,\"x\":0.05}}],\"name\":\"quanquan3\"},{\"display\":[{\"type\":\"image\",\"name\":\"texture_skillactive/quanquan\",\"transform\":{\"x\":0.2}}],\"blendMode\":\"add\",\"name\":\"quanquan\"},{\"display\":[{\"type\":\"image\",\"name\":\"texture_skillactive/q1\",\"transform\":{\"y\":0.2,\"x\":0.2}}],\"name\":\"q1\"},{\"display\":[{\"type\":\"image\",\"name\":\"texture_skillactive/quanquan\",\"transform\":{\"x\":0.2}}],\"blendMode\":\"add\",\"name\":\"quanquan_1\"},{\"display\":[{\"type\":\"image\",\"name\":\"texture_skillactive/liqsli\",\"transform\":{\"y\":0.15,\"x\":0.15}}],\"name\":\"liqsli_1\"},{\"display\":[{\"type\":\"image\",\"name\":\"texture_skillactive/liqsli\",\"transform\":{\"y\":0.15,\"x\":0.15}}],\"name\":\"liqsli\"}]}],\"animation\":[{\"frame\":[],\"slot\":[{\"frame\":[{\"displayIndex\":-1,\"duration\":14,\"tweenEasing\":0,\"color\":{}},{\"duration\":12,\"tweenEasing\":0,\"color\":{\"aM\":40}},{\"duration\":1,\"tweenEasing\":null,\"color\":{\"aM\":0}},{\"displayIndex\":-1,\"duration\":2,\"tweenEasing\":null,\"color\":{}}],\"name\":\"111_1\"},{\"frame\":[{\"displayIndex\":-1,\"duration\":4,\"tweenEasing\":0,\"color\":{}},{\"duration\":8,\"tweenEasing\":0,\"color\":{\"aM\":0}},{\"duration\":7,\"tweenEasing\":0,\"color\":{\"aM\":50}},{\"duration\":1,\"tweenEasing\":null,\"color\":{}},{\"displayIndex\":-1,\"duration\":9,\"tweenEasing\":null,\"color\":{}}],\"name\":\"quanquan_1\"},{\"frame\":[{\"displayIndex\":-1,\"duration\":16,\"tweenEasing\":0,\"color\":{}},{\"duration\":5,\"tweenEasing\":0,\"color\":{\"aM\":35}},{\"duration\":1,\"tweenEasing\":null,\"color\":{\"aM\":0}},{\"displayIndex\":-1,\"duration\":7,\"tweenEasing\":null,\"color\":{}}],\"name\":\"quanquan2_1\"},{\"frame\":[{\"displayIndex\":-1,\"duration\":21,\"tweenEasing\":0,\"color\":{}},{\"duration\":6,\"tweenEasing\":0,\"color\":{}},{\"duration\":1,\"tweenEasing\":null,\"color\":{\"aM\":0}},{\"displayIndex\":-1,\"duration\":1,\"tweenEasing\":null,\"color\":{}}],\"name\":\"ddd_1\"},{\"frame\":[{\"displayIndex\":-1,\"duration\":11,\"tweenEasing\":0,\"color\":{}},{\"duration\":4,\"tweenEasing\":0,\"color\":{\"aM\":35}},{\"duration\":1,\"tweenEasing\":null,\"color\":{\"aM\":35}},{\"displayIndex\":-1,\"duration\":13,\"tweenEasing\":null,\"color\":{}}],\"name\":\"liqsli_1\"},{\"frame\":[{\"duration\":7,\"tweenEasing\":0,\"color\":{}},{\"duration\":7,\"tweenEasing\":0,\"color\":{}},{\"duration\":1,\"tweenEasing\":null,\"color\":{}},{\"displayIndex\":-1,\"duration\":14,\"tweenEasing\":null,\"color\":{}}],\"name\":\"quanquan\"},{\"frame\":[{\"displayIndex\":-1,\"duration\":16,\"tweenEasing\":0,\"color\":{}},{\"duration\":2,\"tweenEasing\":0,\"color\":{\"gM\":37,\"bM\":37,\"rM\":37}},{\"duration\":1,\"tweenEasing\":null,\"color\":{\"aM\":0}},{\"displayIndex\":-1,\"duration\":10,\"tweenEasing\":null,\"color\":{}}],\"name\":\"quanquan3\"},{\"frame\":[{\"displayIndex\":-1,\"duration\":12,\"tweenEasing\":0,\"color\":{}},{\"duration\":5,\"tweenEasing\":0,\"color\":{}},{\"duration\":1,\"tweenEasing\":null,\"color\":{\"aM\":0}},{\"displayIndex\":-1,\"duration\":11,\"tweenEasing\":null,\"color\":{}}],\"name\":\"quanquan2\"},{\"frame\":[{\"displayIndex\":-1,\"duration\":17,\"tweenEasing\":0,\"color\":{}},{\"duration\":6,\"tweenEasing\":0,\"color\":{}},{\"duration\":1,\"tweenEasing\":null,\"color\":{\"aM\":0}},{\"displayIndex\":-1,\"duration\":5,\"tweenEasing\":null,\"color\":{}}],\"name\":\"ddd\"},{\"frame\":[{\"displayIndex\":-1,\"duration\":7,\"tweenEasing\":0,\"color\":{}},{\"duration\":4,\"tweenEasing\":0,\"color\":{}},{\"duration\":1,\"tweenEasing\":null,\"color\":{}},{\"displayIndex\":-1,\"duration\":17,\"tweenEasing\":null,\"color\":{}}],\"name\":\"liqsli\"},{\"frame\":[{\"displayIndex\":-1,\"duration\":11,\"tweenEasing\":0,\"color\":{}},{\"duration\":5,\"tweenEasing\":0,\"color\":{\"aM\":0}},{\"duration\":12,\"tweenEasing\":0,\"color\":{}},{\"duration\":1,\"tweenEasing\":null,\"color\":{\"aM\":0}},{\"displayIndex\":-1,\"duration\":0,\"tweenEasing\":null,\"color\":{}}],\"name\":\"q1\"}],\"duration\":29,\"ffd\":[],\"name\":\"skillactive\",\"bone\":[{\"frame\":[{\"duration\":11,\"transform\":{\"y\":-0.65,\"scX\":1.3514,\"scY\":1.3514,\"x\":0.05},\"tweenEasing\":0},{\"duration\":5,\"transform\":{},\"tweenEasing\":0},{\"duration\":12,\"transform\":{\"scX\":1.3514,\"scY\":1.3514},\"tweenEasing\":0},{\"duration\":1,\"transform\":{\"scX\":3.0135,\"scY\":3.0135},\"tweenEasing\":null},{\"duration\":0,\"transform\":{\"y\":-0.65,\"scX\":1.3514,\"scY\":1.3514,\"x\":0.05},\"tweenEasing\":null}],\"name\":\"q1\"},{\"frame\":[{\"duration\":7,\"transform\":{\"y\":0.95,\"scX\":1.4286,\"scY\":1.4286,\"x\":0.35},\"tweenEasing\":0},{\"duration\":4,\"transform\":{},\"tweenEasing\":0},{\"duration\":1,\"transform\":{\"scX\":4.4571,\"scY\":4.4571},\"tweenEasing\":null},{\"duration\":17,\"transform\":{\"y\":0.95,\"scX\":1.4286,\"scY\":1.4286,\"x\":0.35},\"tweenEasing\":null}],\"name\":\"liqsli\"},{\"frame\":[{\"duration\":17,\"transform\":{\"y\":-1.15,\"x\":-2.7},\"tweenEasing\":0},{\"duration\":6,\"transform\":{},\"tweenEasing\":0},{\"duration\":1,\"transform\":{\"scX\":1.87,\"scY\":1.87},\"tweenEasing\":null},{\"duration\":5,\"transform\":{\"y\":-1.15,\"x\":-2.7},\"tweenEasing\":null}],\"name\":\"ddd\"},{\"frame\":[{\"duration\":12,\"transform\":{\"y\":-0.1,\"scX\":1.3158,\"scY\":1.3158,\"x\":0.05},\"tweenEasing\":0},{\"duration\":5,\"transform\":{},\"tweenEasing\":0},{\"duration\":1,\"transform\":{\"skX\":50.95,\"skY\":50.95,\"scX\":0.5658,\"scY\":0.5658,\"x\":0.05},\"tweenEasing\":null},{\"duration\":11,\"transform\":{\"y\":-0.1,\"scX\":1.3158,\"scY\":1.3158,\"x\":0.05},\"tweenEasing\":null}],\"name\":\"quanquan2\"},{\"frame\":[{\"duration\":16,\"transform\":{\"y\":-1.15,\"scX\":0.6173,\"scY\":0.6173,\"x\":-0.4},\"tweenEasing\":0},{\"duration\":2,\"transform\":{},\"tweenEasing\":0},{\"duration\":1,\"transform\":{\"scX\":2.1296,\"scY\":2.1296},\"tweenEasing\":null},{\"duration\":10,\"transform\":{\"y\":-1.15,\"scX\":0.6173,\"scY\":0.6173,\"x\":-0.4},\"tweenEasing\":null}],\"name\":\"quanquan3\"},{\"frame\":[{\"duration\":7,\"transform\":{},\"tweenEasing\":0},{\"duration\":7,\"transform\":{\"skX\":115.39,\"skY\":115.39,\"y\":0.05,\"scX\":0.7278,\"scY\":0.7278,\"x\":0.05},\"tweenEasing\":0},{\"duration\":1,\"transform\":{\"skX\":274.99,\"skY\":274.99,\"scX\":0.4167,\"scY\":0.4167,\"x\":0.05},\"tweenEasing\":null},{\"duration\":14,\"transform\":{\"skX\":253.52,\"skY\":253.52,\"y\":-0.1,\"scX\":0.5556,\"scY\":0.5556,\"x\":-0.05},\"tweenEasing\":null}],\"name\":\"quanquan\"},{\"frame\":[{\"duration\":11,\"transform\":{\"skX\":-61.2,\"skY\":-61.2,\"y\":0.35,\"scX\":0.7143,\"scY\":0.7143,\"x\":0.1},\"tweenEasing\":0},{\"duration\":4,\"transform\":{},\"tweenEasing\":0},{\"duration\":1,\"transform\":{\"scX\":4.4643,\"scY\":4.4643},\"tweenEasing\":null},{\"duration\":13,\"transform\":{\"skX\":-61.2,\"skY\":-61.2,\"y\":0.35,\"scX\":0.7143,\"scY\":0.7143,\"x\":0.1},\"tweenEasing\":null}],\"name\":\"liqsli_1\"},{\"frame\":[{\"duration\":21,\"transform\":{\"skX\":-61.2,\"skY\":-61.2,\"y\":-3.1,\"scX\":1.25,\"scY\":1.25,\"x\":-1.4},\"tweenEasing\":0},{\"duration\":6,\"transform\":{},\"tweenEasing\":0},{\"duration\":1,\"transform\":{\"y\":-0.1,\"scX\":2.7625,\"scY\":2.7625,\"x\":0.1},\"tweenEasing\":null},{\"duration\":1,\"transform\":{\"skX\":-61.2,\"skY\":-61.2,\"y\":-3.1,\"scX\":1.25,\"scY\":1.25,\"x\":-1.4},\"tweenEasing\":null}],\"name\":\"ddd_1\"},{\"frame\":[{\"duration\":16,\"transform\":{\"skX\":-61.2,\"skY\":-61.2,\"y\":-0.2,\"scX\":1.3158,\"scY\":1.3158,\"x\":-1.05},\"tweenEasing\":0},{\"duration\":5,\"transform\":{},\"tweenEasing\":0},{\"duration\":1,\"transform\":{\"skX\":50.94,\"skY\":50.94,\"y\":0.05,\"scX\":0.5658,\"scY\":0.5658},\"tweenEasing\":null},{\"duration\":7,\"transform\":{\"skX\":-61.2,\"skY\":-61.2,\"y\":-0.2,\"scX\":1.3158,\"scY\":1.3158,\"x\":-1.05},\"tweenEasing\":null}],\"name\":\"quanquan2_1\"},{\"frame\":[{\"duration\":4,\"transform\":{\"skX\":-106.48,\"skY\":-106.48,\"y\":-0.1,\"scX\":0.5556,\"scY\":0.5556,\"x\":-0.05},\"tweenEasing\":0},{\"duration\":8,\"transform\":{},\"tweenEasing\":0},{\"duration\":7,\"transform\":{\"skX\":115.39,\"skY\":115.39,\"y\":0.05,\"scX\":0.7278,\"scY\":0.7278,\"x\":0.05},\"tweenEasing\":0},{\"duration\":1,\"transform\":{\"skX\":274.99,\"skY\":274.99,\"scX\":0.4167,\"scY\":0.4167,\"x\":0.05},\"tweenEasing\":null},{\"duration\":9,\"transform\":{\"skX\":253.52,\"skY\":253.52,\"y\":-0.1,\"scX\":0.5556,\"scY\":0.5556,\"x\":-0.05},\"tweenEasing\":null}],\"name\":\"quanquan_1\"},{\"frame\":[{\"duration\":14,\"transform\":{\"skX\":-61.2,\"skY\":-61.2,\"y\":-0.45,\"scX\":1.5873,\"scY\":1.5873},\"tweenEasing\":0},{\"duration\":12,\"transform\":{},\"tweenEasing\":0},{\"duration\":1,\"transform\":{\"scX\":4.6032,\"scY\":4.6032,\"x\":0.1},\"tweenEasing\":null},{\"duration\":2,\"transform\":{\"skX\":-61.2,\"skY\":-61.2,\"y\":-0.45,\"scX\":1.5873,\"scY\":1.5873},\"tweenEasing\":null}],\"name\":\"111_1\"},{\"frame\":[{\"duration\":29,\"transform\":{},\"tweenEasing\":null}],\"name\":\"root\"}]}],\"ik\":[],\"name\":\"skillactive\",\"bone\":[{\"name\":\"root\",\"transform\":{}},{\"transform\":{\"skX\":106.48,\"skY\":106.48,\"y\":0.1,\"scX\":1.8,\"scY\":1.8,\"x\":0.05},\"name\":\"quanquan\",\"parent\":\"root\"},{\"transform\":{\"y\":-0.95,\"scX\":0.7,\"scY\":0.7,\"x\":-0.35},\"name\":\"liqsli\",\"parent\":\"root\"},{\"transform\":{\"y\":1.15,\"x\":2.7},\"name\":\"ddd\",\"parent\":\"root\"},{\"transform\":{\"y\":0.1,\"scX\":0.76,\"scY\":0.76,\"x\":-0.05},\"name\":\"quanquan2\",\"parent\":\"root\"},{\"transform\":{\"y\":1.15,\"scX\":1.62,\"scY\":1.62,\"x\":0.4},\"name\":\"quanquan3\",\"parent\":\"root\"},{\"transform\":{\"y\":0.65,\"scX\":0.74,\"scY\":0.74,\"x\":-0.05},\"name\":\"q1\",\"parent\":\"root\"},{\"transform\":{\"skX\":61.2,\"skY\":61.2,\"y\":-0.35,\"scX\":1.4,\"scY\":1.4,\"x\":-0.1},\"name\":\"liqsli_1\",\"parent\":\"root\"},{\"transform\":{\"skX\":61.2,\"skY\":61.2,\"y\":3.1,\"scX\":0.8,\"scY\":0.8,\"x\":1.4},\"name\":\"ddd_1\",\"parent\":\"root\"},{\"transform\":{\"skX\":61.2,\"skY\":61.2,\"y\":0.2,\"scX\":0.76,\"scY\":0.76,\"x\":1.05},\"name\":\"quanquan2_1\",\"parent\":\"root\"},{\"transform\":{\"skX\":106.48,\"skY\":106.48,\"y\":0.1,\"scX\":1.8,\"scY\":1.8,\"x\":0.05},\"name\":\"quanquan_1\",\"parent\":\"root\"},{\"transform\":{\"skX\":61.2,\"skY\":61.2,\"y\":0.45,\"scX\":0.63,\"scY\":0.63},\"name\":\"111_1\",\"parent\":\"root\"}]}],\"name\":\"skillactive\",\"version\":\"4.5\",\"isGlobal\":0}"}]
