[{"__type__":"cc.SpriteFrame","content":{"name":"main_blue_btn","texture":"1cfe5e2db","rect":[2,204,149,61],"offset":[0,0],"originalSize":[149,61],"capInsets":[65,25,66,24]}},{"__type__":"cc.SpriteFrame","content":{"name":"ditong","texture":"1cfe5e2db","rect":[369,2,78,41],"offset":[0,0],"originalSize":[78,41],"capInsets":[34,17,34,16]}},{"__type__":"cc.SpriteFrame","content":{"name":"chunheibeijing","texture":"1cfe5e2db","rect":[2,269,8,8],"offset":[0,0],"originalSize":[8,8]}},[{"__type__":"cc.Prefab","_name":"ShareRewardPanel","data":{"__id__":1},"asyncLoadAssets":null},{"__type__":"cc.Node","_name":"ShareRewardPanel","_children":[{"__id__":2},{"__id__":3},{"__id__":4},{"__id__":5},{"__id__":6},{"__id__":7},{"__id__":8},{"__id__":9},{"__id__":10},{"__id__":11},{"__id__":12}],"_components":[{"__type__":"de9bd8TgU5MiZQxTMIv64i5","node":{"__id__":1},"node_items_parent":{"__id__":9},"pre_item_box":{"__uuid__":"d38v5Dwr9Fo56/fcnKvui5"}}],"_prefab":{"__type__":"cc.PrefabInfo","root":{"__id__":1},"asset":{"__uuid__":"7ehG8qIExMK6D+Nm3nD6KC"},"fileId":"b4BRd2PH9HQYPog8Pebks1"}},{"__type__":"cc.Node","_name":"chunheibeijing","_parent":{"__id__":1},"_components":[{"__type__":"cc.Sprite","node":{"__id__":2},"_spriteFrame":{"__uuid__":"59jsb3bLhN/JY628ANNyLt"},"_type":1,"_sizeMode":0},{"__type__":"cc.Button","node":{"__id__":2},"clickEvents":[{"__type__":"cc.ClickEvent","target":{"__id__":1},"component":"DailySharePanel","handler":"goBack"}],"_N$target":{"__id__":2}}],"_prefab":{"__type__":"cc.PrefabInfo","root":{"__id__":1},"asset":{"__uuid__":"7ehG8qIExMK6D+Nm3nD6KC"},"fileId":"ddpHaSuKlHlozhSf87comG"},"_opacity":170,"_contentSize":{"__type__":"cc.Size","width":3000,"height":2000}},{"__type__":"cc.Node","_name":"hero_detail_board_bg","_parent":{"__id__":1},"_components":[{"__type__":"cc.Sprite","node":{"__id__":3},"_spriteFrame":{"__uuid__":"e21x0XttpG/pQkMVaHPVsr"},"_type":1,"_sizeMode":0},{"__type__":"1f8fb3CC4lMGobQL3dMNJK5","node":{"__id__":3}}],"_prefab":{"__type__":"cc.PrefabInfo","root":{"__id__":1},"asset":{"__uuid__":"7ehG8qIExMK6D+Nm3nD6KC"},"fileId":"c8qj1QHGlHHZKmPP3YQ0oi"},"_contentSize":{"__type__":"cc.Size","width":650,"height":400}},{"__type__":"cc.Node","_name":"close","_parent":{"__id__":1},"_components":[{"__type__":"cc.Sprite","node":{"__id__":4},"_spriteFrame":{"__uuid__":"ebZbFbtBpFqou3dRb8+7ly"}},{"__type__":"cc.Button","node":{"__id__":4},"clickEvents":[{"__type__":"cc.ClickEvent","target":{"__id__":1},"component":"DailySharePanel","handler":"goBack"}],"_N$target":{"__id__":4}}],"_prefab":{"__type__":"cc.PrefabInfo","root":{"__id__":1},"asset":{"__uuid__":"7ehG8qIExMK6D+Nm3nD6KC"},"fileId":"c99UcP6xZCS7+AiMvvtUe6"},"_contentSize":{"__type__":"cc.Size","width":68,"height":68},"_position":{"__type__":"cc.Vec2","x":309,"y":186}},{"__type__":"cc.Node","_name":"city_kuang_img_4","_parent":{"__id__":1},"_components":[{"__type__":"cc.Sprite","node":{"__id__":5},"_spriteFrame":{"__uuid__":"89uvn75VlCOIEiJosOsBIO"},"_type":1,"_sizeMode":0}],"_prefab":{"__type__":"cc.PrefabInfo","root":{"__id__":1},"asset":{"__uuid__":"7ehG8qIExMK6D+Nm3nD6KC"},"fileId":"a1McuU9IhDCYT2IpH8e+yC"},"_contentSize":{"__type__":"cc.Size","width":250,"height":66},"_position":{"__type__":"cc.Vec2","y":216.6}},{"__type__":"cc.Node","_name":"frame11","_parent":{"__id__":1},"_components":[{"__type__":"cc.Sprite","node":{"__id__":6},"_spriteFrame":{"__uuid__":"e7hNl2Nc9MZbOJZe7V4lGL"},"_type":1,"_sizeMode":0}],"_prefab":{"__type__":"cc.PrefabInfo","root":{"__id__":1},"asset":{"__uuid__":"7ehG8qIExMK6D+Nm3nD6KC"},"fileId":"3a285uqLZA4qDmvTbQi9sI"},"_contentSize":{"__type__":"cc.Size","width":550,"height":250},"_position":{"__type__":"cc.Vec2","y":-47}},{"__type__":"cc.Node","_name":"main_blue_btn","_parent":{"__id__":1},"_components":[{"__type__":"cc.Sprite","node":{"__id__":7},"_spriteFrame":{"__uuid__":"15VKoQqBRLLZ8Wq6hqaPY3"},"_type":1,"_sizeMode":0},{"__type__":"cc.Button","node":{"__id__":7},"clickEvents":[{"__type__":"cc.ClickEvent","target":{"__id__":1},"component":"DailySharePanel","handler":"clickHandler_share"}],"_N$target":{"__id__":7}}],"_prefab":{"__type__":"cc.PrefabInfo","root":{"__id__":1},"asset":{"__uuid__":"7ehG8qIExMK6D+Nm3nD6KC"},"fileId":"88G3E2afFA6q4wNIg6QlDG"},"_contentSize":{"__type__":"cc.Size","width":160,"height":70},"_position":{"__type__":"cc.Vec2","y":-124}},{"__type__":"cc.Node","_name":"ditong","_parent":{"__id__":1},"_components":[{"__type__":"cc.Sprite","node":{"__id__":8},"_spriteFrame":{"__uuid__":"25txTYiAdAg5qdIonWNsS/"},"_type":1,"_sizeMode":0}],"_prefab":{"__type__":"cc.PrefabInfo","root":{"__id__":1},"asset":{"__uuid__":"7ehG8qIExMK6D+Nm3nD6KC"},"fileId":"e204p2D7NIHro3ylxZC4If"},"_contentSize":{"__type__":"cc.Size","width":525,"height":88},"_position":{"__type__":"cc.Vec2","y":135}},{"__type__":"cc.Node","_name":"enemy list Layout","_parent":{"__id__":1},"_components":[{"__type__":"cc.Layout","node":{"__id__":9},"_layoutSize":{"__type__":"cc.Size","width":530,"height":210},"_resize":1,"_N$layoutType":3,"_N$spacingX":10,"_N$spacingY":12}],"_prefab":{"__type__":"cc.PrefabInfo","root":{"__id__":1},"asset":{"__uuid__":"7ehG8qIExMK6D+Nm3nD6KC"},"fileId":"8b5dQeQtFGjJcboh4v92Lj"},"_anchorPoint":{"__type__":"cc.Vec2","x":0.5,"y":1},"_contentSize":{"__type__":"cc.Size","width":530,"height":210},"_position":{"__type__":"cc.Vec2","y":64}},{"__type__":"cc.Node","_name":"New Label","_parent":{"__id__":1},"_components":[{"__type__":"cc.Label","node":{"__id__":10},"_useOriginalSize":false,"_actualFontSize":24,"_fontSize":24,"_lineHeight":28,"_N$string":"Phút hưởng","_N$horizontalAlign":1,"_N$verticalAlign":1}],"_prefab":{"__type__":"cc.PrefabInfo","root":{"__id__":1},"asset":{"__uuid__":"7ehG8qIExMK6D+Nm3nD6KC"},"fileId":"aaYxNEYgZBg73FAQg3N7cC"},"_contentSize":{"__type__":"cc.Size","width":54.67,"height":28},"_position":{"__type__":"cc.Vec2","y":-122}},{"__type__":"cc.Node","_name":"New Label","_parent":{"__id__":1},"_components":[{"__type__":"cc.Label","node":{"__id__":11},"_useOriginalSize":false,"_actualFontSize":24,"_fontSize":24,"_lineHeight":28,"_N$string":"mỗi ngày chia xẻ","_N$horizontalAlign":1,"_N$verticalAlign":1}],"_prefab":{"__type__":"cc.PrefabInfo","root":{"__id__":1},"asset":{"__uuid__":"7ehG8qIExMK6D+Nm3nD6KC"},"fileId":"f93QufBqJCLJBMAAvmXsda"},"_contentSize":{"__type__":"cc.Size","width":96,"height":28},"_position":{"__type__":"cc.Vec2","y":217.6}},{"__type__":"cc.Node","_name":"New Label","_parent":{"__id__":1},"_components":[{"__type__":"cc.Label","node":{"__id__":12},"_useOriginalSize":false,"_actualFontSize":24,"_fontSize":24,"_lineHeight":28,"_N$string":"mỗi ngày chia xẻ cung cấp phong phú phần thưởng ，trăm ngàn không nên bỏ qua ！\nchia xẻ sau khi hoàn thành phần thưởng tự động gửi đi ！","_N$verticalAlign":1}],"_prefab":{"__type__":"cc.PrefabInfo","root":{"__id__":1},"asset":{"__uuid__":"7ehG8qIExMK6D+Nm3nD6KC"},"fileId":"2c9yD1uOVIL4CNhe/QWCDF"},"_contentSize":{"__type__":"cc.Size","width":480,"height":56},"_position":{"__type__":"cc.Vec2","y":135}}],{"__type__":"cc.SpriteFrame","content":{"name":"title_bg","texture":"1cfe5e2db","rect":[215,2,150,66],"offset":[0,0],"originalSize":[150,66],"capInsets":[67,0,67,0]}},{"__type__":"cc.SpriteFrame","content":{"name":"hero_detail_board_bg","texture":"1cfe5e2db","rect":[2,2,209,126],"offset":[0,0],"originalSize":[209,126],"capInsets":[92,57,94,56]}},{"__type__":"cc.SpriteFrame","content":{"name":"frame11","texture":"1cfe5e2db","rect":[215,72,113,47],"offset":[0,0],"originalSize":[113,47],"capInsets":[50,15,51,14]}},{"__type__":"cc.SpriteFrame","content":{"name":"close","texture":"1cfe5e2db","rect":[2,132,68,68],"offset":[0,0],"originalSize":[68,68]}}]
