{"__type__":"dragonBones.DragonBonesAtlasAsset","_name":"cavalry_4_red","_atlasJson":"{\"name\":\"cavalry_4_red\",\"imagePath\":\"battleunits.png\",\"SubTexture\":[{\"name\":\"cavalry_4_red_assault1\",\"x\":1193,\"y\":46,\"width\":81,\"height\":74},{\"name\":\"cavalry_4_red_assault2\",\"x\":1276,\"y\":80,\"width\":79,\"height\":72},{\"name\":\"cavalry_4_red_assault3\",\"x\":1348,\"y\":217,\"width\":78,\"height\":75},{\"name\":\"cavalry_4_red_assault4\",\"x\":1268,\"y\":199,\"width\":78,\"height\":79},{\"name\":\"cavalry_4_red_attack1\",\"x\":1678,\"y\":195,\"width\":69,\"height\":76},{\"name\":\"cavalry_4_red_attack2\",\"x\":1009,\"y\":100,\"width\":81,\"height\":66},{\"name\":\"cavalry_4_red_die1\",\"x\":2,\"y\":752,\"width\":72,\"height\":78},{\"name\":\"cavalry_4_red_die2\",\"x\":1512,\"y\":229,\"width\":69,\"height\":71},{\"name\":\"cavalry_4_red_die3\",\"x\":298,\"y\":708,\"width\":72,\"height\":63},{\"name\":\"cavalry_4_red_hurt1\",\"x\":1750,\"y\":182,\"width\":69,\"height\":76},{\"name\":\"cavalry_4_red_hurt2\",\"x\":1735,\"y\":331,\"width\":68,\"height\":78},{\"name\":\"cavalry_4_red_move1\",\"x\":559,\"y\":616,\"width\":73,\"height\":75},{\"name\":\"cavalry_4_red_move2\",\"x\":229,\"y\":538,\"width\":76,\"height\":75},{\"name\":\"cavalry_4_red_move3\",\"x\":484,\"y\":594,\"width\":73,\"height\":75},{\"name\":\"cavalry_4_red_move4\",\"x\":145,\"y\":714,\"width\":72,\"height\":77},{\"name\":\"cavalry_4_red_stand1\",\"x\":1522,\"y\":150,\"width\":69,\"height\":77},{\"name\":\"cavalry_4_red_victory1\",\"x\":588,\"y\":451,\"width\":66,\"height\":80},{\"name\":\"cavalry_4_red_victory2\",\"x\":76,\"y\":786,\"width\":67,\"height\":93},{\"name\":\"cavalry_4_red_victory3\",\"x\":566,\"y\":533,\"width\":73,\"height\":81}]}\n","texture":{"__uuid__":"aa2sKZWPxIhIOoamfWesSu"}}
