{"__type__":"dragonBones.DragonBonesAtlasAsset","_name":"pikeman_2_red","_atlasJson":"{\"name\":\"pikeman_2_red\",\"imagePath\":\"battleunits.png\",\"SubTexture\":[{\"name\":\"pikeman_2_red_assault1\",\"x\":1077,\"y\":387,\"width\":66,\"height\":36},{\"name\":\"pikeman_2_red_assault2\",\"x\":1849,\"y\":614,\"width\":66,\"height\":39},{\"name\":\"pikeman_2_red_assault3\",\"x\":1157,\"y\":370,\"width\":66,\"height\":36},{\"name\":\"pikeman_2_red_assault4\",\"x\":1919,\"y\":588,\"width\":66,\"height\":39},{\"name\":\"pikeman_2_red_attack1\",\"x\":1748,\"y\":899,\"width\":58,\"height\":40},{\"name\":\"pikeman_2_red_attack2\",\"x\":53,\"y\":1220,\"width\":49,\"height\":38},{\"name\":\"pikeman_2_red_attack3\",\"x\":494,\"y\":448,\"width\":77,\"height\":37},{\"name\":\"pikeman_2_red_die1\",\"x\":276,\"y\":820,\"width\":54,\"height\":45},{\"name\":\"pikeman_2_red_die2\",\"x\":731,\"y\":649,\"width\":61,\"height\":30},{\"name\":\"pikeman_2_red_hurt1\",\"x\":145,\"y\":793,\"width\":55,\"height\":43},{\"name\":\"pikeman_2_red_hurt2\",\"x\":1074,\"y\":885,\"width\":45,\"height\":40},{\"name\":\"pikeman_2_red_move1\",\"x\":275,\"y\":1052,\"width\":51,\"height\":38},{\"name\":\"pikeman_2_red_move2\",\"x\":511,\"y\":1106,\"width\":51,\"height\":40},{\"name\":\"pikeman_2_red_move3\",\"x\":564,\"y\":1124,\"width\":51,\"height\":38},{\"name\":\"pikeman_2_red_move4\",\"x\":222,\"y\":1013,\"width\":51,\"height\":40},{\"name\":\"pikeman_2_red_stand1\",\"x\":132,\"y\":927,\"width\":54,\"height\":39},{\"name\":\"pikeman_2_red_victory1\",\"x\":691,\"y\":981,\"width\":38,\"height\":57},{\"name\":\"pikeman_2_red_victory2\",\"x\":1934,\"y\":833,\"width\":31,\"height\":77},{\"name\":\"pikeman_2_red_victory3\",\"x\":459,\"y\":1257,\"width\":31,\"height\":65}]}\n","texture":{"__uuid__":"aa2sKZWPxIhIOoamfWesSu"}}
