{"__type__":"cc.SpriteAtlas","_spriteFrames":{"titleBg_light":{"__uuid__":"38FGeD/xlK0ZMKY66t7wag"},"title_jlwp":{"__uuid__":"6cdSuK/ghMCrv6GtSGqh3N"},"title_wbfl":{"__uuid__":"beAGCCappJB5NmghLkhWzE"},"frame4_2":{"__uuid__":"e5lPVbUCtCX4SyCCtf1Woh"},"title_wblb":{"__uuid__":"89Y2VFrslFoYScODHmAA7g"},"images_17_libao_2":{"__uuid__":"6b+ZS0VXVBdaYIud4OKLhV"},"qedj_title":{"__uuid__":"3cyOXZnh1O+YlxBbsJG/46"},"images_17_libao_3":{"__uuid__":"3cEk0B71dFqLmnGpum4BEr"},"images_17_libao_4":{"__uuid__":"964VSePUJOaKcG5ZRzO25B"},"btn1":{"__uuid__":"3ey9qtzMhMyouDafj8RtIC"},"btn2":{"__uuid__":"b1kcZeNydC+J57XOTy8TJs"},"images_17_libao_5":{"__uuid__":"b1ICZSGWBI9oFYrfQBNLCv"},"iconMask":{"__uuid__":"15cCvpD75NF79JeW6qtWNC"}}}
